dsclient/__init__.py
dsclient/core.py
dsclient/utils.py
dsclient/version.py
dsclient-0.2.0.dist-info/LICENSE
dsclient-0.2.0.dist-info/METADATA
dsclient-0.2.0.dist-info/WHEEL
dsclient-0.2.0.dist-info/top_level.txt
dsclient-0.2.0.dist-info/RECORD
