Metadata-Version: 2.1
Name: dsclient
Version: 0.2.0
Summary: Python Client for debugserver-js
Home-page: https://dsclient-py.readthedocs.io
Author: Cameron Webb
Author-email: webbjcam@gmail.com
License: MIT
Download-URL: https://github.com/tiflash/dsclient-py/tarball/0.2.0
Project-URL: Documentation, https://dsclient-py.readthedocs.io
Project-URL: Source, https://github.com/tiflash/dsclient-py
Platform: UNKNOWN
Classifier: Development Status :: 5 - Production/Stable
Classifier: License :: OSI Approved :: MIT License
Classifier: Operating System :: OS Independent
Classifier: Programming Language :: Python :: 2.7
Classifier: Programming Language :: Python :: 3.6
Classifier: Programming Language :: Python :: 3.7
Classifier: Topic :: Software Development :: Embedded Systems
Classifier: Topic :: Software Development :: Libraries :: Python Modules
Classifier: Topic :: Software Development :: Testing
Classifier: Intended Audience :: Developers
Requires-Python: >=2.7.13, <4
